Workbook

Sheet 程序及说明
D2: 财税处理流程（混用进项转出）
C4: 一、 | D4: 政策概述以及依据：
D5: 1.政策概述：a.当长期资产如固定资产、无形资产、不动产等用于公司经营，对应的收入涉及到一般计税方法计税项目，又用于简易计税方法计税项目、免征增值税项目、非应税交易、集体福利或个人消费等
E6: 五类不允许抵扣进项的情形，须按照收入的比例对增值税进项进行转出处理。
E7: b.一般纳税人购进货物 (不含固定资产)、服务，用于简易计税方法计税项目、免征增值税项目而无法划分不得抵扣的进项税额。
D8: 2.政策要求：企业需建立完善的资产用途台账和进项税分摊台账。
D9: 3.申报要求：先逐期归集数据，逐期计算并暂估转出金额。年度汇算清算调整，汇总全年的全部进项税额、应税与免税及简易计税项目的总销售额，重新核算全年应转出的进项税额
D10: 4.政策依据：国家税务总局官网,通过国家税务总局官网（https://www.chinatax.gov.cn）的 “互动交流 — 意见征集” 栏目，检索对应征求意见稿的发布内容
E11: (1).《中华人民共和国增值税法实施条例（征求意见稿）》其他货物、服务混用的年度清算（第二十三条）
E12: 一般纳税人购进货物 (不含固定资产)、服务，用于简易计税方法计税项目、免征增值税项目而无法划分不得抵扣的进项税额，按照下列公式计算当期不得抵扣的进项税额：
E13: 当期不得抵扣的进项税额 = 当期无法划分的全部进项税额 ×(当期简易计税方法计税项目销售额 + 当期免征增值税项目销售额)÷ 当期全部销售额。
E14: 纳税人应当按照上述公式逐期计算不得抵扣的进项税额，并在次年 1 月纳税申报期内依据全年汇总数据进行清算调整。
E15: (2).《中华人民共和国增值税法实施条例（征求意见稿）》长期资产混用的汇算调整（第二十六条）
E16: 固定资产、无形资产或者不动产同时用于一般计税方法计税项目和简易计税方法计税项目、免征增值税项目、非应税交易、集体福利或者个人消费的，其进项税额按照下列规定处理：
E17: 单项原值不超过 500 万元的，进项税额可以全额从销项税额中抵扣；
E18: 单项原值超过 500 万元的，购进时其进项税额可以全额从销项税额中抵扣，混合用途期间，应当根据折旧或者摊销年限，计算不得抵扣项目对应的进项税额并逐年调整转出。
C20: 二、 | D20: 建议流程
D21: 1.拆解收入构成：可以通过科目设置或者收入台账拆分应税收入以及其他五项不允许进项抵扣收入。
D22: 2.确认进项发票对应的收入项目：按照采购内容区别对应的项目成本费用，建议建立发票台账进行登记。
D23: 3.计算须转出的混合收入对应进项：月度末核算混合收入项目的进项转出额。
D24: 4.申报进项转出：按月申报进项转出。
D25: 5.年度汇算混合收入对应进项：结合其他需要进项转出的事项，对发票台账进行梳理确认，以免错报漏报。
D26: 6.填写申报表：确保申报表数字和工作底稿一致。
C28: 三、 | D28: 注意事项
D29: 1.注意每月的进项转出额过大会影响应交增值税，对现金流产生一定影响。
D30: 2.年度汇算清缴，须保留可查的支持性文件，以便应对税务检查。
C32: 四、 | D32: 其他参考说明：
D33: 1.简易计税方法计税项目：这类计税方法下增值税应纳税额按销售额乘以征收率直接计算，计税逻辑无需进项税额抵扣，比如小规模纳税人通常适用的计税方式对应的相关项目。
D34: 2.免征增值税项目：即享受增值税免税优惠的业务项目，由于此类项目本身不产生销项税额，若允许抵扣进项税额会破坏增值税计税链条的完整性，例如部分符合政策的农产品初加工免税项目等。
D35: 3.非应税交易：对应《增值税法》中规定的不征收增值税的交易行为，如员工为受雇单位提供取得工资的服务、收取行政事业性收费、取得存款利息收入等无增值税应税义务，其对应的进项税额自然无法抵扣。
D36: 4.集体福利：指企业为员工提供的各类集体性福利相关项目，如单位建设的员工食堂、发放的集体宿舍用品、组织员工集体体检等所涉及的资产及相关支出对应的项目。
D37: 5.个人消费：既包括员工个人的消费行为，也涵盖纳税人的交际应酬消费等，如企业购置用于员工个人使用的非生产经营类物品，或是用于个人商务接待的相关物资及服务对应的项目。
D38: 6.固定资产：原值<=500万元的单项长期资产，对应的进项税额可以全额从销项税额中抵扣，无需进项转出。
E39: 原值>500万元的单项长期资产，购进时先全额抵扣进项税额，同时在混合用途期间，应当根据折旧或者摊销年限，再计算五类不允许抵扣项目对应的不得从销项税额中抵扣的进项税额，逐年调整。
D40: 7.转换用途：若长期资产在可抵扣与不可抵扣项目间变更用途，将按照改变当期的期初净值，核算确定允许抵扣和需转出的进项税额。 | E40: 若长期资产在可抵扣与不可抵扣项目间变更用途，将按照改变当期的期初净值，核算确定允许抵扣和需转出的进项税额。

Sheet 进项转出汇总表
C2: 进项转出汇总表
B3: 序号 | C3: 项目 | D3: 1月 | E3: 2月 | F3: 3月 | G3: 4月 | H3: 5月 | I3: 6月 | J3: 7月 | K3: 8月 | L3: 9月 | M3: 10月 | N3: 11月 | O3: 12月 | Q3: 年度汇算
B4: 一、 | C4: 混用情况下应进项转出： | D4: =SUM(D5:D14) -> #DIV/0! | E4: =SUM(E5:E14) -> #DIV/0! | F4: =SUM(F5:F14) -> #DIV/0! | G4: =SUM(G5:G14) -> #DIV/0! | H4: =SUM(H5:H14) -> #DIV/0! | I4: =SUM(I5:I14) -> #DIV/0! | J4: =SUM(J5:J14) -> #DIV/0! | K4: =SUM(K5:K14) -> #DIV/0! | ... O4: =SUM(O5:O14) -> #DIV/0! | Q4: =SUM(Q5:Q14) -> 0
C5: 项目1 | D5: =项目1!D34 -> #DIV/0! | E5: =项目1!E34 -> #DIV/0! | F5: =项目1!F34 -> #DIV/0! | G5: =项目1!G34 -> #DIV/0! | H5: =项目1!H34 -> #DIV/0! | I5: =项目1!I34 -> #DIV/0! | J5: =项目1!J34 -> #DIV/0! | K5: =项目1!K34 -> #DIV/0! | ... O5: =项目1!O34 -> #DIV/0! | Q5: =项目1!Q20 -> 0
C6: 项目2 | D6: =项目2!D34 -> #DIV/0! | E6: =项目2!E34 -> #DIV/0! | F6: =项目2!F34 -> #DIV/0! | G6: =项目2!G34 -> #DIV/0! | H6: =项目2!H34 -> #DIV/0! | I6: =项目2!I34 -> #DIV/0! | J6: =项目2!J34 -> #DIV/0! | K6: =项目2!K34 -> #DIV/0! | ... O6: =项目2!O34 -> #DIV/0! | Q6: =项目2!Q22 -> 0
C7: 项目3 | Q7: =SUM(D7:O7) -> 0
C8: 项目4 | Q8: =SUM(D8:O8) -> 0
C9: 项目5 | Q9: =SUM(D9:O9) -> 0
C10: 项目6 | Q10: =SUM(D10:O10) -> 0
C11: 项目7 | Q11: =SUM(D11:O11) -> 0
C12: 项目8 | Q12: =SUM(D12:O12) -> 0
C13: 项目9 | Q13: =SUM(D13:O13) -> 0
C14: 项目10 | Q14: =SUM(D14:O14) -> 0
B15: 二、 | C15: 其他进项转出（非混用） | D15: 300 | E15: 300 | F15: 300 | G15: 300 | H15: 300 | I15: 300 | J15: 300 | K15: 300 | L15: 300 | M15: 300 | N15: 300 | O15: 300 | Q15: =SUM(D15:O15) -> 3600
B16: 三、 | C16: 当期须转出的进项额 | D16: =D4+D15 -> #DIV/0! | E16: =E4+E15 -> #DIV/0!
B17: 四、 | C17: 年度须转出的进项额 | Q17: =Q4+Q15 -> 3600
B18: 五、 | C18: 已转出的进项额（根据申报表） | D18: 200 | E18: 201 | Q18: =SUM(D18:O18) -> 401
B19: 六、 | C19: 须调整的转出进项额 | D19: =D16-D18 -> #DIV/0! | E19: =E16-E18 -> #DIV/0! | F19: =F16-F18 -> 0 | G19: =G16-G18 -> 0 | H19: =H16-H18 -> 0 | I19: =I16-I18 -> 0 | J19: =J16-J18 -> 0 | K19: =K16-K18 -> 0 | ... O19: =O16-O18 -> 0 | Q19: =Q17-Q18 -> 3199

Sheet 项目1
C2: * 表格黄色部分为填写区域 | D2: 预转出
B3: 序号 | C3: 项目 | D3: 1月 | E3: 2月 | F3: 3月 | G3: 4月 | H3: 5月 | I3: 6月 | J3: 7月 | K3: 8月 | L3: 9月 | M3: 10月 | N3: 11月 | O3: 12月 | P3: 合计 | Q3: 年度汇算(调整）
C4: 混用情况下相应收入的进项转出：
B5: 一、 | C5: 其他货物、服务混用相关
B6: 1 | C6: 其他货物、服务混用相关收入 | D6: =D7+D8 -> 1500 | E6: =E7+E8 -> 2000 | F6: =F7+F8 -> 3000 | G6: =G7+G8 -> 5000 | H6: =H7+H8 -> 6000 | I6: =I7+I8 -> 2000 | J6: =J7+J8 -> 4000 | K6: =K7+K8 -> 3000 | ... O6: =O7+O8 -> 4000 | P6: =SUM(D6:O6) -> 44500 | Q6: =P6 -> 44500
C7: 一般计税方法计税项目收入 | D7: 1000 | E7: 1000 | F7: 2000 | G7: 4000 | H7: 5000 | I7: 1000 | J7: 3000 | K7: 2000 | L7: 4000 | M7: 5000 | N7: 2000 | O7: 3000 | P7: =SUM(D7:O7) -> 33000 | Q7: =P7 -> 33000
C8: 不允许抵扣项目产生的收入 | D8: =SUM(D9:D10) -> 500 | E8: =SUM(E9:E10) -> 1000 | F8: =SUM(F9:F10) -> 1000 | G8: =SUM(G9:G10) -> 1000 | H8: =SUM(H9:H10) -> 1000 | I8: =SUM(I9:I10) -> 1000 | J8: =SUM(J9:J10) -> 1000 | K8: =SUM(K9:K10) -> 1000 | ... P8: =SUM(P9:P10) -> 11500 | Q8: =P8 -> 11500
B9: a. | C9: 简易计税方法计税项目 | D9: 200 | E9: 500 | F9: 500 | G9: 500 | H9: 500 | I9: 500 | J9: 500 | K9: 500 | L9: 500 | M9: 500 | N9: 500 | O9: 500 | P9: =SUM(D9:O9) -> 5700 | Q9: =P9 -> 5700
B10: b. | C10: 免征增值税项目 | D10: 300 | E10: 500 | F10: 500 | G10: 500 | H10: 500 | I10: 500 | J10: 500 | K10: 500 | L10: 500 | M10: 500 | N10: 500 | O10: 500 | P10: =SUM(D10:O10) -> 5800 | Q10: =P10 -> 5800
B11: 2 | C11: 占比 | D11: =D8/D6 -> 0.33333333 | E11: =E8/E6 -> 0.5 | F11: =F8/F6 -> 0.33333333 | G11: =G8/G6 -> 0.2 | H11: =H8/H6 -> 0.16666667 | I11: =I8/I6 -> 0.5 | J11: =J8/J6 -> 0.25 | K11: =K8/K6 -> 0.33333333 | ... P11: =P8/P6 -> 0.25842697 | Q11: =P11 -> 0.25842697
B12: 3 | C12: 混用项目的相关进项额 | D12: =SUM(D13:D15) -> 400 | E12: =SUM(E13:E15) -> 250 | F12: =SUM(F13:F15) -> 300 | G12: =SUM(G13:G15) -> 300 | H12: =SUM(H13:H15) -> 300 | I12: =SUM(I13:I15) -> 300 | J12: =SUM(J13:J15) -> 300 | K12: =SUM(K13:K15) -> 300 | ... P12: =SUM(P13:P15) -> 300 | Q12: =P12 -> 300
C13: 发票1：（发票号） | D13: 100 | E13: 50 | F13: 100 | G13: 100 | H13: 100 | I13: 100 | J13: 100 | K13: 100 | L13: 100 | M13: 100 | N13: 100 | O13: 100 | P13: 100 | Q13: =P13 -> 100
C14: 发票2：（发票号） | D14: 200 | E14: 100 | F14: 100 | G14: 100 | H14: 100 | I14: 100 | J14: 100 | K14: 100 | L14: 100 | M14: 100 | N14: 100 | O14: 100 | P14: 100 | Q14: =P14 -> 100
C15: 发票3：（发票号） | D15: 100 | E15: 100 | F15: 100 | G15: 100 | H15: 100 | I15: 100 | J15: 100 | K15: 100 | L15: 100 | M15: 100 | N15: 100 | O15: 100 | P15: 100 | Q15: =P15 -> 100
B16: 4 | C16: 混用项目的相关进项额 | D16: =D12*D11 -> 133.33333 | E16: =E12*E11 -> 125 | F16: =F12*F11 -> 100 | G16: =G12*G11 -> 60 | H16: =H12*H11 -> 50 | I16: =I12*I11 -> 150 | J16: =J12*J11 -> 75 | K16: =K12*K11 -> 100 | ... Q16: =Q12*Q11 -> 77.52809
B18: 二、 | C18: 长期资产混用相关 | Q18: =P18 -> 0
B19: 1 | C19: 长期资产混用相关收入 | D19: =D20+D21 -> 0 | E19: =E20+E21 -> 0 | F19: =F20+F21 -> 0 | G19: =G20+G21 -> 0 | H19: =H20+H21 -> 0 | I19: =I20+I21 -> 0 | J19: =J20+J21 -> 0 | K19: =K20+K21 -> 0 | ... P19: =P20+P21 -> 0 | Q19: =P19 -> 0
C20: 一般计税方法计税项目 | P20: =SUM(D20:O20) -> 0 | Q20: =P20 -> 0
C21: 不允许抵扣项目产生的收入 | D21: =SUM(D22:D26) -> 0 | E21: =SUM(E22:E26) -> 0 | F21: =SUM(F22:F26) -> 0 | G21: =SUM(G22:G26) -> 0 | H21: =SUM(H22:H26) -> 0 | I21: =SUM(I22:I26) -> 0 | J21: =SUM(J22:J26) -> 0 | K21: =SUM(K22:K26) -> 0 | ... P21: =SUM(P22:P26) -> 0 | Q21: =P21 -> 0
B22: a. | C22: 简易计税方法计税项目 | P22: =SUM(D22:O22) -> 0 | Q22: =P22 -> 0
B23: b. | C23: 免征增值税项目 | P23: =SUM(D23:O23) -> 0 | Q23: =P23 -> 0
B24: c. | C24: 非应税交易 | P24: =SUM(D24:O24) -> 0 | Q24: =P24 -> 0
B25: d. | C25: 集体福利 | P25: =SUM(D25:O25) -> 0 | Q25: =P25 -> 0
B26: e. | C26: 个人消费 | P26: =SUM(D26:O26) -> 0 | Q26: =P26 -> 0
B27: 2 | C27: 占比 | D27: =D21/D19 -> #DIV/0! | E27: =E21/E19 -> #DIV/0! | F27: =F21/F19 -> #DIV/0! | G27: =G21/G19 -> #DIV/0! | H27: =H21/H19 -> #DIV/0! | I27: =I21/I19 -> #DIV/0! | J27: =J21/J19 -> #DIV/0! | K27: =K21/K19 -> #DIV/0! | ... Q27: =Q21/Q19 -> #DIV/0!
B28: 3 | C28: 混用项目的相关进项额 | D28: =SUM(D29:D31) -> 0 | E28: =SUM(E29:E31) -> 0 | F28: =SUM(F29:F31) -> 0 | G28: =SUM(G29:G31) -> 0 | H28: =SUM(H29:H31) -> 0 | I28: =SUM(I29:I31) -> 0 | J28: =SUM(J29:J31) -> 0 | K28: =SUM(K29:K31) -> 0 | ... P28: =SUM(P29:P31) -> 0 | Q28: =P28 -> 0
C29: 发票1：（发票号） | Q29: =P29 -> 0
C30: 发票2：（发票号） | Q30: =P30 -> 0
C31: 发票3：（发票号） | Q31: =P31 -> 0
B32: 4 | C32: 混用项目的相关进项额 | D32: =D27*D28 -> #DIV/0! | E32: =E28*E27 -> #DIV/0! | F32: =F28*F27 -> #DIV/0! | G32: =G28*G27 -> #DIV/0! | H32: =H28*H27 -> #DIV/0! | I32: =I28*I27 -> #DIV/0! | J32: =J28*J27 -> #DIV/0! | K32: =K28*K27 -> #DIV/0! | L32: =L28*L27 -> #DIV/0! | ... P32: =P28*P27 -> #DIV/0! | Q32: =Q27+Q28 -> #DIV/0!
B34: 三、 | C34: 当期混用须转出的进项额 | D34: =D16+D32 -> #DIV/0! | E34: =E16+E32 -> #DIV/0! | F34: =F16+F32 -> #DIV/0! | G34: =G16+G32 -> #DIV/0! | H34: =H16+H32 -> #DIV/0! | I34: =I16+I32 -> #DIV/0! | J34: =J16+J32 -> #DIV/0! | K34: =K16+K32 -> #DIV/0! | ... P34: =P16+P32 -> #DIV/0!
B35: 四、 | C35: 全年混用须转出的进项额 | Q35: =Q32+Q16 -> #DIV/0!
B36: 五、 | C36: 混用项目已转出的进项额（根据申报表） | Q36: =P36 -> 0
B37: 六、 | C37: 须调整的转出进项额 | D37: =D34-D36 -> #DIV/0! | E37: =E34-E36 -> #DIV/0! | F37: =F34-F36 -> #DIV/0! | G37: =G34-G36 -> #DIV/0! | H37: =H34-H36 -> #DIV/0! | I37: =I34-I36 -> #DIV/0! | J37: =J34-J36 -> #DIV/0! | K37: =K34-K36 -> #DIV/0! | ... P37: =P34-P36 -> #DIV/0! | Q37: =Q35-Q36 -> #DIV/0!

Sheet 项目2
C2: * 表格黄色部分为填写区域 | D2: 预转出
B3: 序号 | C3: 项目 | D3: 1月 | E3: 2月 | F3: 3月 | G3: 4月 | H3: 5月 | I3: 6月 | J3: 7月 | K3: 8月 | L3: 9月 | M3: 10月 | N3: 11月 | O3: 12月 | P3: 合计 | Q3: 年度汇算(调整）
C4: 混用情况下相应收入的进项转出：
B5: 一、 | C5: 其他货物、服务混用相关
B6: 1 | C6: 其他货物、服务混用相关收入 | D6: =D7+D8 -> 1500 | E6: =E7+E8 -> 2000 | F6: =F7+F8 -> 3000 | G6: =G7+G8 -> 5000 | H6: =H7+H8 -> 6000 | I6: =I7+I8 -> 2000 | J6: =J7+J8 -> 4000 | K6: =K7+K8 -> 3000 | ... O6: =O7+O8 -> 4000 | P6: =SUM(D6:O6) -> 44500 | Q6: =P6 -> 44500
C7: 一般计税方法计税项目收入 | D7: 1000 | E7: 1000 | F7: 2000 | G7: 4000 | H7: 5000 | I7: 1000 | J7: 3000 | K7: 2000 | L7: 4000 | M7: 5000 | N7: 2000 | O7: 3000 | P7: =SUM(D7:O7) -> 33000 | Q7: =P7 -> 33000
C8: 不允许抵扣项目产生的收入 | D8: =SUM(D9:D10) -> 500 | E8: =SUM(E9:E10) -> 1000 | F8: =SUM(F9:F10) -> 1000 | G8: =SUM(G9:G10) -> 1000 | H8: =SUM(H9:H10) -> 1000 | I8: =SUM(I9:I10) -> 1000 | J8: =SUM(J9:J10) -> 1000 | K8: =SUM(K9:K10) -> 1000 | ... P8: =SUM(P9:P10) -> 11500 | Q8: =P8 -> 11500
B9: a. | C9: 简易计税方法计税项目 | D9: 200 | E9: 500 | F9: 500 | G9: 500 | H9: 500 | I9: 500 | J9: 500 | K9: 500 | L9: 500 | M9: 500 | N9: 500 | O9: 500 | P9: =SUM(D9:O9) -> 5700 | Q9: =P9 -> 5700
B10: b. | C10: 免征增值税项目 | D10: 300 | E10: 500 | F10: 500 | G10: 500 | H10: 500 | I10: 500 | J10: 500 | K10: 500 | L10: 500 | M10: 500 | N10: 500 | O10: 500 | P10: =SUM(D10:O10) -> 5800 | Q10: =P10 -> 5800
B11: 2 | C11: 占比 | D11: =D8/D6 -> 0.33333333 | E11: =E8/E6 -> 0.5 | F11: =F8/F6 -> 0.33333333 | G11: =G8/G6 -> 0.2 | H11: =H8/H6 -> 0.16666667 | I11: =I8/I6 -> 0.5 | J11: =J8/J6 -> 0.25 | K11: =K8/K6 -> 0.33333333 | ... P11: =P8/P6 -> 0.25842697 | Q11: =P11 -> 0.25842697
B12: 3 | C12: 混用项目的相关进项额 | D12: =SUM(D13:D15) -> 400 | E12: =SUM(E13:E15) -> 250 | F12: =SUM(F13:F15) -> 300 | G12: =SUM(G13:G15) -> 300 | H12: =SUM(H13:H15) -> 300 | I12: =SUM(I13:I15) -> 300 | J12: =SUM(J13:J15) -> 300 | K12: =SUM(K13:K15) -> 300 | ... P12: =SUM(P13:P15) -> 300 | Q12: =P12 -> 300
C13: 发票1：（发票号） | D13: 100 | E13: 50 | F13: 100 | G13: 100 | H13: 100 | I13: 100 | J13: 100 | K13: 100 | L13: 100 | M13: 100 | N13: 100 | O13: 100 | P13: 100 | Q13: =P13 -> 100
C14: 发票2：（发票号） | D14: 200 | E14: 100 | F14: 100 | G14: 100 | H14: 100 | I14: 100 | J14: 100 | K14: 100 | L14: 100 | M14: 100 | N14: 100 | O14: 100 | P14: 100 | Q14: =P14 -> 100
C15: 发票3：（发票号） | D15: 100 | E15: 100 | F15: 100 | G15: 100 | H15: 100 | I15: 100 | J15: 100 | K15: 100 | L15: 100 | M15: 100 | N15: 100 | O15: 100 | P15: 100 | Q15: =P15 -> 100
B16: 4 | C16: 混用项目的相关进项额 | D16: =D12*D11 -> 133.33333 | E16: =E12*E11 -> 125 | F16: =F12*F11 -> 100 | G16: =G12*G11 -> 60 | H16: =H12*H11 -> 50 | I16: =I12*I11 -> 150 | J16: =J12*J11 -> 75 | K16: =K12*K11 -> 100 | ... Q16: =Q12*Q11 -> 77.52809
B18: 二、 | C18: 长期资产混用相关 | Q18: =P18 -> 0
B19: 1 | C19: 长期资产混用相关收入 | D19: =D20+D21 -> 0 | E19: =E20+E21 -> 0 | F19: =F20+F21 -> 0 | G19: =G20+G21 -> 0 | H19: =H20+H21 -> 0 | I19: =I20+I21 -> 0 | J19: =J20+J21 -> 0 | K19: =K20+K21 -> 0 | ... P19: =P20+P21 -> 0 | Q19: =P19 -> 0
C20: 一般计税方法计税项目 | P20: =SUM(D20:O20) -> 0 | Q20: =P20 -> 0
C21: 不允许抵扣项目产生的收入 | D21: =SUM(D22:D26) -> 0 | E21: =SUM(E22:E26) -> 0 | F21: =SUM(F22:F26) -> 0 | G21: =SUM(G22:G26) -> 0 | H21: =SUM(H22:H26) -> 0 | I21: =SUM(I22:I26) -> 0 | J21: =SUM(J22:J26) -> 0 | K21: =SUM(K22:K26) -> 0 | ... P21: =SUM(P22:P26) -> 0 | Q21: =P21 -> 0
B22: a. | C22: 简易计税方法计税项目 | P22: =SUM(D22:O22) -> 0 | Q22: =P22 -> 0
B23: b. | C23: 免征增值税项目 | P23: =SUM(D23:O23) -> 0 | Q23: =P23 -> 0
B24: c. | C24: 非应税交易 | P24: =SUM(D24:O24) -> 0 | Q24: =P24 -> 0
B25: d. | C25: 集体福利 | P25: =SUM(D25:O25) -> 0 | Q25: =P25 -> 0
B26: e. | C26: 个人消费 | P26: =SUM(D26:O26) -> 0 | Q26: =P26 -> 0
B27: 2 | C27: 占比 | D27: =D21/D19 -> #DIV/0! | E27: =E21/E19 -> #DIV/0! | F27: =F21/F19 -> #DIV/0! | G27: =G21/G19 -> #DIV/0! | H27: =H21/H19 -> #DIV/0! | I27: =I21/I19 -> #DIV/0! | J27: =J21/J19 -> #DIV/0! | K27: =K21/K19 -> #DIV/0! | ... Q27: =Q21/Q19 -> #DIV/0!
B28: 3 | C28: 混用项目的相关进项额 | D28: =SUM(D29:D31) -> 0 | E28: =SUM(E29:E31) -> 0 | F28: =SUM(F29:F31) -> 0 | G28: =SUM(G29:G31) -> 0 | H28: =SUM(H29:H31) -> 0 | I28: =SUM(I29:I31) -> 0 | J28: =SUM(J29:J31) -> 0 | K28: =SUM(K29:K31) -> 0 | ... P28: =SUM(P29:P31) -> 0 | Q28: =P28 -> 0
C29: 发票1：（发票号） | Q29: =P29 -> 0
C30: 发票2：（发票号） | Q30: =P30 -> 0
C31: 发票3：（发票号） | Q31: =P31 -> 0
B32: 4 | C32: 混用项目的相关进项额 | D32: =D27*D28 -> #DIV/0! | E32: =E28*E27 -> #DIV/0! | F32: =F28*F27 -> #DIV/0! | G32: =G28*G27 -> #DIV/0! | H32: =H28*H27 -> #DIV/0! | I32: =I28*I27 -> #DIV/0! | J32: =J28*J27 -> #DIV/0! | K32: =K28*K27 -> #DIV/0! | L32: =L28*L27 -> #DIV/0! | ... P32: =P28*P27 -> #DIV/0! | Q32: =Q27+Q28 -> #DIV/0!
B34: 三、 | C34: 当期混用须转出的进项额 | D34: =D16+D32 -> #DIV/0! | E34: =E16+E32 -> #DIV/0! | F34: =F16+F32 -> #DIV/0! | G34: =G16+G32 -> #DIV/0! | H34: =H16+H32 -> #DIV/0! | I34: =I16+I32 -> #DIV/0! | J34: =J16+J32 -> #DIV/0! | K34: =K16+K32 -> #DIV/0! | ... P34: =P16+P32 -> #DIV/0!
B35: 四、 | C35: 全年混用须转出的进项额 | Q35: =Q32+Q16 -> #DIV/0!
B36: 五、 | C36: 混用项目已转出的进项额（根据申报表） | Q36: =P36 -> 0
B37: 六、 | C37: 须调整的转出进项额 | D37: =D34-D36 -> #DIV/0! | E37: =E34-E36 -> #DIV/0! | F37: =F34-F36 -> #DIV/0! | G37: =G34-G36 -> #DIV/0! | H37: =H34-H36 -> #DIV/0! | I37: =I34-I36 -> #DIV/0! | J37: =J34-J36 -> #DIV/0! | K37: =K34-K36 -> #DIV/0! | ... P37: =P34-P36 -> #DIV/0! | Q37: =Q35-Q36 -> #DIV/0!
